ssm_dox/__init__.py
ssm_dox/_cli/__init__.py
ssm_dox/_cli/commands/__init__.py
ssm_dox/_cli/commands/_build.py
ssm_dox/_cli/commands/_check.py
ssm_dox/_cli/commands/_publish.py
ssm_dox/_cli/commands/utils.py
ssm_dox/_cli/logs.py
ssm_dox/_cli/main.py
ssm_dox/_logging.py
ssm_dox/constants.py
ssm_dox/document.py
ssm_dox/dox.py
ssm_dox/exceptions.py
ssm_dox/finder.py
ssm_dox/mixins.py
ssm_dox/models/__init__.py
ssm_dox/models/base.py
ssm_dox/models/document.py
ssm_dox/models/main_steps/__init__.py
ssm_dox/models/main_steps/aws_runpowershellscript.py
ssm_dox/models/main_steps/aws_runshellscript.py
ssm_dox/models/main_steps/base.py
ssm_dox/models/parameter.py
ssm_dox-0.2.0.dist-info/entry_points.txt
ssm_dox-0.2.0.dist-info/LICENSE
ssm_dox-0.2.0.dist-info/WHEEL
ssm_dox-0.2.0.dist-info/METADATA
ssm_dox-0.2.0.dist-info/RECORD
