Metadata-Version: 2.1
Name: ssm-dox
Version: 0.2.0
Summary: CLI tool for building and publishing SSM Documents.
Home-page: https://github.com/ITProKyle/ssm-dox
License: Apache-2.0
Keywords: cli
Author: Kyle Finley
Author-email: kyle@finley.sh
Requires-Python: >=3.8,<4.0
Classifier: Development Status :: 4 - Beta
Classifier: Intended Audience :: Developers
Classifier: License :: OSI Approved :: Apache Software License
Classifier: Natural Language :: English
Classifier: Operating System :: POSIX
Classifier: Programming Language :: Python :: 3
Classifier: Programming Language :: Python :: 3 :: Only
Classifier: Programming Language :: Python :: 3.10
Classifier: Programming Language :: Python :: 3.8
Classifier: Programming Language :: Python :: 3.9
Classifier: Topic :: Utilities
Provides-Extra: docs
Requires-Dist: PyYAML (>=5.4)
Requires-Dist: Sphinx (>=3.5.2,<4.0.0); extra == "docs"
Requires-Dist: boto3 (>=1.19,<2.0)
Requires-Dist: click (>=8.0.1,<9.0.0)
Requires-Dist: coloredlogs (>=15.0,<16.0)
Requires-Dist: pydantic (>=1.8.1,<2.0.0)
Requires-Dist: readthedocs-sphinx-search (>=0.1.0,<0.2.0); extra == "docs"
Requires-Dist: sphinx-rtd-theme (>=0.5.1,<0.6.0); extra == "docs"
Requires-Dist: toml (>=0.10.2,<0.11.0); extra == "docs"
Project-URL: Bug Tracker, https://github.com/ITProKyle/ssm-dox/issues
Project-URL: Repository, https://github.com/ITProKyle/ssm-dox
